calautograder/project/check.py
calautograder/project/freezerestore/__init__.py
calautograder/project/freezerestore/freeze.py
calautograder/project/freezerestore/restore.py
calautograder/project/make_project.py
calautograder/project/submit.py
calautograder-0.0.1.9.dist-info/entry_points.txt
calautograder-0.0.1.9.dist-info/LICENSE
calautograder-0.0.1.9.dist-info/WHEEL
calautograder-0.0.1.9.dist-info/METADATA
calautograder-0.0.1.9.dist-info/RECORD
