Metadata-Version: 2.1
Name: calautograder
Version: 0.0.1.9
Summary: commandline autograder implimentation
License: GPLv3
Author: Nick Brown
Author-email: bicknrown@gmail.com
Requires-Python: >=3.8,<4.0
Classifier: License :: Other/Proprietary License
Classifier: Programming Language :: Python :: 3
Classifier: Programming Language :: Python :: 3.8
Classifier: Programming Language :: Python :: 3.9
